lingo/__init__.py
lingo/cli.py
lingo/context.py
lingo/core.py
lingo/embed.py
lingo/engine.py
lingo/flow.py
lingo/fsm.py
lingo/llm.py
lingo/mock.py
lingo/prompts.py
lingo/skills.py
lingo/state.py
lingo/tools.py
lingo/utils.py
lingo_ai-1.3.dist-info/METADATA
lingo_ai-1.3.dist-info/WHEEL
lingo_ai-1.3.dist-info/licenses/LICENSE
lingo_ai-1.3.dist-info/RECORD
