Metadata-Version: 2.4
Name: lingo-ai
Version: 1.3
Summary: A minimal, async-native, and unopinionated toolkit for modern LLM applications.
Author-email: Alejandro Piad <apiad@apiad.net>
License-File: LICENSE
Classifier: License :: OSI Approved :: MIT License
Classifier: Operating System :: OS Independent
Classifier: Programming Language :: Python :: 3.12
Classifier: Topic :: Software Development :: Libraries :: Application Frameworks
Requires-Python: >=3.12
Requires-Dist: openai>=2.7.2
Requires-Dist: purely>=1.0
Requires-Dist: pydantic>=2.12.4
Requires-Dist: pyyaml>=6.0.3
